pamqualeLabsTasks/__init__.py
pamqualeLabsTasks/lab9.py
pamqualeLabsTasks-0.0.1.dist-info/LICENSE.txt
pamqualeLabsTasks-0.0.1.dist-info/METADATA
pamqualeLabsTasks-0.0.1.dist-info/WHEEL
pamqualeLabsTasks-0.0.1.dist-info/top_level.txt
pamqualeLabsTasks-0.0.1.dist-info/RECORD
