Metadata-Version: 2.1
Name: pamqualeLabsTasks
Version: 0.0.1
Summary: Python package for lab tasks
Home-page: 
Author: Pamquale Tagaromus
Author-email: pamquale@gmail.com
License: MIT
Keywords: lab tasks
Classifier: Development Status :: 5 - Production/Stable
Classifier: Intended Audience :: Developers
Classifier: License :: OSI Approved :: MIT License
Classifier: Programming Language :: Python :: 3
License-File: LICENSE.txt
